{"IcoMoonType":"selection","icons":[{"icon":{"paths":["M558.777 1024l-463.314-463.102c-53.607-58.313-86.466-136.435-86.466-222.232 0-181.601 147.216-328.817 328.817-328.817 85.85 0 164.015 32.9 222.576 86.78l-0.234-0.212c59.259-59.259 141.125-95.912 231.551-95.912 180.852 0 327.462 146.61 327.462 327.462 0 90.426-36.652 172.292-95.912 231.551l-0 0z"],"attrs":[{}],"width":1120,"isMulticolor":false,"isMulticolor2":false,"grid":0,"tags":["Risorsa 16 (2)mdpi"]},"attrs":[{}],"properties":{"order":26,"id":0,"name":"iccuore-pieno","prevSize":32,"code":59648},"setIdx":0,"setId":11,"iconIdx":0}],"height":1024,"metadata":{"name":"icomoon"},"preferences":{"showGlyphs":true,"showQuickUse":true,"showQuickUse2":true,"showSVGs":true,"fontPref":{"prefix":"icon-","metadata":{"fontFamily":"icomoon"},"metrics":{"emSize":1024,"baseline":6.25,"whitespace":50},"embed":false},"imagePref":{"prefix":"icon-","png":true,"useClassSelector":true,"color":0,"bgColor":16777215,"classSelector":".icon"},"historySize":50,"showCodes":true,"gridSize":16}}